{
  "title": "📚 Сцена 6: Любовь в трагедии",
  "icon": "💕",
  "quote": "Люблю вас я, как долг велит, — не больше и не меньше",
  "emotions": [
    "Истинная любовь",
    "Отцовская нежность",
    "Страсть и предательство",
    "Верность сердца"
  ],
  "vocabulary": [
    {
      "german": "die Liebe",
      "transcription": "[ди ЛИ-бе]",
      "translation": "любовь",
      "type": "существительное",
      "character_voice": {
        "character": "Корделия",
        "german": "Die wahre Liebe spricht nicht viel",
        "russian": "Истинная любовь не многословна"
      },
      "gesture": {
        "icon": "❤️",
        "gesture": "Рука на сердце",
        "emotion": "ИСКРЕННОСТЬ",
        "association": "Корделия говорит о своей ЛЮБВИ без лести, только правду"
      }
    },
    {
      "german": "das Herz",
      "transcription": "[дас ХЕРЦ]",
      "translation": "сердце",
      "type": "существительное",
      "character_voice": {
        "character": "Лир",
        "german": "Mein Herz bricht!",
        "russian": "Моё сердце разрывается!"
      },
      "gesture": {
        "icon": "💔",
        "gesture": "Хватается за грудь",
        "emotion": "БОЛЬ",
        "association": "Лир чувствует, как его СЕРДЦЕ разбивается от предательства дочерей"
      }
    },
    {
      "german": "lieben",
      "transcription": "[ЛИ-бен]",
      "translation": "любить",
      "type": "глагол",
      "character_voice": {
        "character": "Гонерилья",
        "german": "Ich liebe Euch mehr als mein Leben!",
        "russian": "Я люблю вас больше жизни!"
      },
      "gesture": {
        "icon": "🎭",
        "gesture": "Театральный поклон",
        "emotion": "ЛИЦЕМЕРИЕ",
        "association": "Гонерилья лживо клянется ЛЮБИТЬ отца больше зрения и свободы"
      }
    },
    {
      "german": "der Kuss",
      "transcription": "[дер КУС]",
      "translation": "поцелуй",
      "type": "существительное",
      "character_voice": {
        "character": "Регана",
        "german": "Ein Kuss des Verrats",
        "russian": "Поцелуй предательства"
      },
      "gesture": {
        "icon": "😘",
        "gesture": "Воздушный поцелуй",
        "emotion": "ФАЛЬШЬ",
        "association": "Регана целует отца в щёку перед тем, как выгнать его в бурю"
      }
    },
    {
      "german": "umarmen",
      "transcription": "[ум-АР-мен]",
      "translation": "обнимать",
      "type": "глагол",
      "character_voice": {
        "character": "Корделия",
        "german": "Lass mich dich umarmen, Vater",
        "russian": "Позволь обнять тебя, отец"
      },
      "gesture": {
        "icon": "🤗",
        "gesture": "Раскрытые объятия",
        "emotion": "ПРОЩЕНИЕ",
        "association": "Корделия ОБНИМАЕТ безумного отца в финальной встрече"
      }
    },
    {
      "german": "die Treue",
      "transcription": "[ди ТРОЙ-е]",
      "translation": "верность",
      "type": "существительное",
      "character_voice": {
        "character": "Кент",
        "german": "Meine Treue gehört dem wahren König",
        "russian": "Моя верность принадлежит истинному королю"
      },
      "gesture": {
        "icon": "🛡️",
        "gesture": "Рука на мече",
        "emotion": "ПРЕДАННОСТЬ",
        "association": "Кент хранит ВЕРНОСТЬ Лиру даже в изгнании"
      }
    },
    {
      "german": "heiraten",
      "transcription": "[ХАЙ-ра-тен]",
      "translation": "выходить замуж",
      "type": "глагол",
      "character_voice": {
        "character": "Корделия",
        "german": "Wenn ich heirate, teile ich meine Liebe",
        "russian": "Когда выйду замуж, разделю свою любовь"
      },
      "gesture": {
        "icon": "💍",
        "gesture": "Показывает кольцо",
        "emotion": "ЧЕСТНОСТЬ",
        "association": "Корделия говорит, что ВЫЙДЯ ЗАМУЖ, будет любить и мужа тоже"
      }
    },
    {
      "german": "die Leidenschaft",
      "transcription": "[ди ЛАЙ-ден-шафт]",
      "translation": "страсть",
      "type": "существительное",
      "character_voice": {
        "character": "Эдмунд",
        "german": "Die Leidenschaft treibt mich voran",
        "russian": "Страсть движет мною"
      },
      "gesture": {
        "icon": "🔥",
        "gesture": "Сжатый кулак",
        "emotion": "ЖАЖДА",
        "association": "Эдмунд полон СТРАСТИ к власти и обеим сёстрам"
      }
    },
    {
      "german": "zärtlich",
      "transcription": "[ЦЕРТ-лих]",
      "translation": "нежный",
      "type": "прилагательное",
      "character_voice": {
        "character": "Лир",
        "german": "Sei zärtlich mit mir, Kind",
        "russian": "Будь нежна со мной, дитя"
      },
      "gesture": {
        "icon": "🕊️",
        "gesture": "Гладит по голове",
        "emotion": "НЕЖНОСТЬ",
        "association": "Безумный Лир просит Корделию быть НЕЖНОЙ с ним"
      }
    },
    {
      "german": "verzeihen",
      "transcription": "[фер-ЦАЙ-ен]",
      "translation": "прощать",
      "type": "глагол",
      "character_voice": {
        "character": "Корделия",
        "german": "Ich verzeihe dir alles",
        "russian": "Я прощаю тебе всё"
      },
      "gesture": {
        "icon": "🙏",
        "gesture": "Складывает руки",
        "emotion": "МИЛОСЕРДИЕ",
        "association": "Корделия ПРОЩАЕТ отца за изгнание и проклятия"
      }
    },
    {
      "german": "die Eifersucht",
      "transcription": "[ди АЙ-фер-зухт]",
      "translation": "ревность",
      "type": "существительное",
      "character_voice": {
        "character": "Гонерилья",
        "german": "Die Eifersucht vergiftet mich",
        "russian": "Ревность отравляет меня"
      },
      "gesture": {
        "icon": "💚",
        "gesture": "Стискивает зубы",
        "emotion": "ЗАВИСТЬ",
        "association": "Гонерилья испытывает РЕВНОСТЬ к сестре из-за Эдмунда"
      }
    },
    {
      "german": "verlassen",
      "transcription": "[фер-ЛА-сен]",
      "translation": "покидать",
      "type": "глагол",
      "character_voice": {
        "character": "Лир",
        "german": "Alle haben mich verlassen!",
        "russian": "Все меня покинули!"
      },
      "gesture": {
        "icon": "🚪",
        "gesture": "Отворачивается",
        "emotion": "ОДИНОЧЕСТВО",
        "association": "Лир чувствует себя ПОКИНУТЫМ всеми, кого любил"
      }
    }
  ],
  "story": {
    "title": "ТЕАТРАЛЬНЫЙ МОМЕНТ",
    "content": "<p>Тронный зал. Старый король требует доказательств <span class=\"story-highlight\">die Liebe (любви)</span> от дочерей. Гонерилья и Регана лицемерно клянутся в безграничной преданности, их <span class=\"story-highlight\">die Küsse (поцелуи)</span> фальшивы как их слова.</p>\n<p>Но младшая Корделия говорит правду: когда она <span class=\"story-highlight\">heiraten wird (выйдет замуж)</span>, её <span class=\"story-highlight\">das Herz (сердце)</span> будет принадлежать и мужу тоже. Лир в ярости <span class=\"story-highlight\">verlässt (покидает)</span> её, не понимая, что только она <span class=\"story-highlight\">liebt (любит)</span> искренне.</p>\n<p>Позже, в буре безумия, он поймёт истину. Корделия <span class=\"story-highlight\">umarmt (обнимет)</span> его с <span class=\"story-highlight\">zärtlich (нежностью)</span> и <span class=\"story-highlight\">verzeiht (простит)</span> всё. Но <span class=\"story-highlight\">die Leidenschaft (страсть)</span> и <span class=\"story-highlight\">die Eifersucht (ревность)</span> старших сестёр к Эдмунду приведёт к трагедии.</p>\n<p>Только граф Кент сохранит <span class=\"story-highlight\">die Treue (верность)</span> до конца, следуя за изгнанным королём в его скитаниях. Любовь в этой пьесе - и спасение, и проклятие.</p>",
    "emotional_peak": "Корделия целует мёртвого отца: 'Эти губы больше не заговорят...'"
  },
  "dialogues": [
    {
      "character": "КОРОЛЬ ЛИР",
      "german": "Welche von euch LIEBT mich am meisten? Sprecht aus eurem HERZEN!",
      "russian": "Которая из вас ЛЮБИТ меня больше всех? Говорите от СЕРДЦА!",
      "emotion": "👑 [Властно, ожидая лести]"
    },
    {
      "character": "ГОНЕРИЛЬЯ",
      "german": "Vater, meine LIEBE zu Euch ist größer als Worte. Ich würde niemals HEIRATEN, um bei Euch zu bleiben!",
      "russian": "Отец, моя ЛЮБОВЬ к вам больше слов. Я никогда не ВЫЙДУ ЗАМУЖ, чтобы остаться с вами!",
      "emotion": "🎭 [Лживо, театрально]"
    },
    {
      "character": "РЕГАНА",
      "german": "Ich LIEBE Euch mit solcher LEIDENSCHAFT! Nehmt diesen KUSS als Zeichen meiner TREUE!",
      "russian": "Я ЛЮБЛЮ вас с такой СТРАСТЬЮ! Примите этот ПОЦЕЛУЙ как знак моей ВЕРНОСТИ!",
      "emotion": "😘 [Притворно страстно]"
    },
    {
      "character": "КОРДЕЛИЯ",
      "german": "Ich liebe Euch wie eine Tochter sollte. Wenn ich HEIRATE, wird mein HERZ geteilt sein.",
      "russian": "Я люблю вас как должна дочь. Когда ВЫЙДУ ЗАМУЖ, моё СЕРДЦЕ будет разделено.",
      "emotion": "💔 [Честно, спокойно]"
    },
    {
      "character": "КОРОЛЬ ЛИР",
      "german": "Was?! Du willst mich VERLASSEN? Deine Worte sind nicht ZÄRTLICH! Wo ist deine LIEBE?",
      "russian": "Что?! Ты хочешь меня ПОКИНУТЬ? Твои слова не НЕЖНЫ! Где твоя ЛЮБОВЬ?",
      "emotion": "😡 [В шоке и гневе]"
    },
    {
      "character": "КЕНТ",
      "german": "Meine TREUE gehört Euch, mein König! Die wahre LIEBE spricht leise!",
      "russian": "Моя ВЕРНОСТЬ принадлежит вам, мой король! Истинная ЛЮБОВЬ говорит тихо!",
      "emotion": "🛡️ [Преданно, смело]"
    },
    {
      "character": "КОРДЕЛИЯ (в финале)",
      "german": "Vater, ich VERZEIHE dir alles. Lass mich dich UMARMEN, sei ZÄRTLICH in meinen Armen.",
      "russian": "Отец, я ПРОЩАЮ тебе всё. Позволь мне тебя ОБНЯТЬ, будь НЕЖЕН в моих объятиях.",
      "emotion": "🕊️ [С безграничной любовью]"
    },
    {
      "character": "ГОНЕРИЛЬЯ (о Эдмунде)",
      "german": "Diese LEIDENSCHAFT! Diese EIFERSUCHT! Ich würde alle VERLASSEN für ihn!",
      "russian": "Эта СТРАСТЬ! Эта РЕВНОСТЬ! Я бы всех ПОКИНУЛА ради него!",
      "emotion": "🔥 [Одержимо, страстно]"
    }
  ],
  "memory_trick": {
    "master_trick": "Представь испытание любви в тронном зале. ЛЮБОВЬ требует доказательств - \n                лживые ПОЦЕЛУИ сестёр против честного СЕРДЦА Корделии. \n                Она ВЫЙДЕТ ЗАМУЖ и разделит любовь - отец её ПОКИДАЕТ. \n                Но ВЕРНОСТЬ Кента неизменна. В финале - ОБЪЯТИЯ, НЕЖНОСТЬ, ПРОЩЕНИЕ. \n                А СТРАСТЬ и РЕВНОСТЬ сестёр к Эдмунду погубит всех.",
    "emotion_chain": "Испытание → Ложь → Правда → Отвержение → Верность → Безумие → Прощение → Смерть",
    "ritual": "Сыграй сцену испытания любви. Будь Гонерильей (лживая любовь), \n                потом Корделией (честная любовь), потом Лиром (требующим любви). \n                Почувствуй разницу между истинной и ложной любовью!"
  },
  "level": "a2",
  "group": "gruppe_2_emotionen",
  "id": "06_Любовь_A2",
  "cheat_sheet": [
    {
      "german": "die Liebe",
      "russian": "любовь",
      "emotion_moment": "ИСКРЕННОСТЬ",
      "gesture_anchor": "❤️ Рука на сердце",
      "character_moment": "Корделия"
    },
    {
      "german": "das Herz",
      "russian": "сердце",
      "emotion_moment": "БОЛЬ",
      "gesture_anchor": "💔 Хватается за грудь",
      "character_moment": "Лир"
    },
    {
      "german": "lieben",
      "russian": "любить",
      "emotion_moment": "ЛИЦЕМЕРИЕ",
      "gesture_anchor": "🎭 Театральный поклон",
      "character_moment": "Гонерилья"
    },
    {
      "german": "der Kuss",
      "russian": "поцелуй",
      "emotion_moment": "ФАЛЬШЬ",
      "gesture_anchor": "😘 Воздушный поцелуй",
      "character_moment": "Регана"
    },
    {
      "german": "umarmen",
      "russian": "обнимать",
      "emotion_moment": "ПРОЩЕНИЕ",
      "gesture_anchor": "🤗 Раскрытые объятия",
      "character_moment": "Корделия"
    },
    {
      "german": "die Treue",
      "russian": "верность",
      "emotion_moment": "ПРЕДАННОСТЬ",
      "gesture_anchor": "🛡️ Рука на мече",
      "character_moment": "Кент"
    },
    {
      "german": "heiraten",
      "russian": "выходить замуж",
      "emotion_moment": "ЧЕСТНОСТЬ",
      "gesture_anchor": "💍 Показывает кольцо",
      "character_moment": "Корделия"
    },
    {
      "german": "die Leidenschaft",
      "russian": "страсть",
      "emotion_moment": "ЖАЖДА",
      "gesture_anchor": "🔥 Сжатый кулак",
      "character_moment": "Эдмунд"
    },
    {
      "german": "zärtlich",
      "russian": "нежный",
      "emotion_moment": "НЕЖНОСТЬ",
      "gesture_anchor": "🕊️ Гладит по голове",
      "character_moment": "Лир"
    },
    {
      "german": "verzeihen",
      "russian": "прощать",
      "emotion_moment": "МИЛОСЕРДИЕ",
      "gesture_anchor": "🙏 Складывает руки",
      "character_moment": "Корделия"
    },
    {
      "german": "die Eifersucht",
      "russian": "ревность",
      "emotion_moment": "ЗАВИСТЬ",
      "gesture_anchor": "💚 Стискивает зубы",
      "character_moment": "Гонерилья"
    },
    {
      "german": "verlassen",
      "russian": "покидать",
      "emotion_moment": "ОДИНОЧЕСТВО",
      "gesture_anchor": "🚪 Отворачивается",
      "character_moment": "Лир"
    }
  ],
  "exercise": {
    "title": "🎭 Заповніть пропуски в театральній постановці",
    "text": "<p>Тронный зал. Старый король требует доказательств <span class=\"story-highlight\">___ (любви)</span> от дочерей. Гонерилья и Регана лицемерно клянутся в безграничной преданности, их <span class=\"story-highlight\">___ (поцелуи)</span> фальшивы как их слова.</p>\n<p>Но младшая Корделия говорит правду: когда она <span class=\"story-highlight\">___ (выйдет замуж)</span>, её <span class=\"story-highlight\">___ (сердце)</span> будет принадлежать и мужу тоже. Лир в ярости <span class=\"story-highlight\">___ (покидает)</span> её, не понимая, что только она <span class=\"story-highlight\">___ (любит)</span> искренне.</p>\n<p>Позже, в буре безумия, он поймёт истину. Корделия <span class=\"story-highlight\">___ (обнимет)</span> его с <span class=\"story-highlight\">___ (нежностью)</span> и <span class=\"story-highlight\">___ (простит)</span> всё. Но <span class=\"story-highlight\">___ (страсть)</span> и <span class=\"story-highlight\">___ (ревность)</span> старших сестёр к Эдмунду приведёт к трагедии.</p>\n<p>Только граф Кент сохранит <span class=\"story-highlight\">___ (верность)</span> до конца, следуя за изгнанным королём в его скитаниях. Любовь в этой пьесе - и спасение, и проклятие.</p>",
    "answers": {
      "любви": "der Liebe",
      "поцелуи": "die Küsse",
      "выйдет замуж": "heiraten wird",
      "сердце": "das Herz",
      "покидает": "verlässt",
      "любит": "liebt",
      "обнимет": "umarmt",
      "нежностью": "Zärtlichkeit",
      "простит": "verzeiht",
      "страсть": "die Leidenschaft",
      "ревность": "die Eifersucht",
      "верность": "die Treue"
    }
  }
}